localized_fields/__init__.py
localized_fields/admin.py
localized_fields/apps.py
localized_fields/descriptor.py
localized_fields/expressions.py
localized_fields/forms.py
localized_fields/lookups.py
localized_fields/mixins.py
localized_fields/models.py
localized_fields/util.py
localized_fields/value.py
localized_fields/widgets.py
localized_fields/fields/__init__.py
localized_fields/fields/autoslug_field.py
localized_fields/fields/bleach_field.py
localized_fields/fields/char_field.py
localized_fields/fields/field.py
localized_fields/fields/file_field.py
localized_fields/fields/float_field.py
localized_fields/fields/integer_field.py
localized_fields/fields/text_field.py
localized_fields/fields/uniqueslug_field.py
localized_fields/migrations/0001_initial.py
localized_fields/migrations/__init__.py
localized_fields/static/localized_fields/localized-fields-admin.css
localized_fields/static/localized_fields/localized-fields-admin.js
localized_fields/templates/localized_fields/multiwidget.html
localized_fields/templates/localized_fields/admin/widget.html
django_localized_fields-6.6.dist-info/LICENSE.md
django_localized_fields-6.6.dist-info/METADATA
django_localized_fields-6.6.dist-info/WHEEL
django_localized_fields-6.6.dist-info/top_level.txt
django_localized_fields-6.6.dist-info/RECORD
