Metadata-Version: 2.1
Name: django-localized-fields
Version: 6.6
Summary: Implementation of localized model fields using PostgreSQL HStore fields.
Home-page: https://github.com/SectorLabs/django-localized-fields
Author: Sector Labs
Author-email: open-source@sectorlabs.ro
License: MIT License
Keywords: django,localized,language,models,fields,postgres,hstore,i18n
Platform: UNKNOWN
Classifier: Environment :: Web Environment
Classifier: Framework :: Django
Classifier: Intended Audience :: Developers
Classifier: License :: OSI Approved :: MIT License
Classifier: Operating System :: OS Independent
Classifier: Programming Language :: Python
Classifier: Programming Language :: Python :: 3.6
Classifier: Programming Language :: Python :: 3.7
Classifier: Programming Language :: Python :: 3.8
Classifier: Programming Language :: Python :: 3.9
Classifier: Topic :: Internet :: WWW/HTTP
Classifier: Topic :: Internet :: WWW/HTTP :: Dynamic Content
Requires-Python: >=3.6
License-File: LICENSE.md
Requires-Dist: Django (>=2.0)
Requires-Dist: django-postgres-extra (<3.0,>=2.0)
Requires-Dist: deprecation (==2.0.7)
Requires-Dist: dataclasses ; python_version <= "3.6"
Provides-Extra: analysis
Requires-Dist: black (==19.3b0) ; extra == 'analysis'
Requires-Dist: flake8 (==3.7.7) ; extra == 'analysis'
Requires-Dist: autoflake (==1.3) ; extra == 'analysis'
Requires-Dist: autopep8 (==1.4.4) ; extra == 'analysis'
Requires-Dist: isort (==4.3.20) ; extra == 'analysis'
Requires-Dist: sl-docformatter (==1.4) ; extra == 'analysis'
Provides-Extra: docs
Requires-Dist: Sphinx (==2.2.0) ; extra == 'docs'
Requires-Dist: sphinx-rtd-theme (==0.4.3) ; extra == 'docs'
Provides-Extra: test
Requires-Dist: tox (==3.14.3) ; extra == 'test'
Requires-Dist: pytest (==5.3.2) ; extra == 'test'
Requires-Dist: pytest-django (==3.7.0) ; extra == 'test'
Requires-Dist: pytest-cov (==2.8.1) ; extra == 'test'
Requires-Dist: dj-database-url (==0.5.0) ; extra == 'test'
Requires-Dist: django-autoslug (==1.9.6) ; extra == 'test'
Requires-Dist: django-bleach (==0.6.1) ; extra == 'test'
Requires-Dist: psycopg2 (==2.8.4) ; extra == 'test'
